yyx/__init__.py
yyx/module_a.py
yyx/module_b.py
yyx-0.1.0.dist-info/LICENSE.txt
yyx-0.1.0.dist-info/METADATA
yyx-0.1.0.dist-info/WHEEL
yyx-0.1.0.dist-info/top_level.txt
yyx-0.1.0.dist-info/RECORD
