Metadata-Version: 2.1
Name: yyx
Version: 0.1.0
Summary: 一个用于数学建模的工具包，包含数据处理和分析功能
Home-page: 
Author: ZengHao
Author-email: 2718621328@qq.com
License: MIT
Classifier: License :: OSI Approved :: MIT License
Classifier: Programming Language :: Python
Classifier: Programming Language :: Python :: 3.8
Classifier: Programming Language :: Python :: Implementation :: CPython
Classifier: Programming Language :: Python :: Implementation :: PyPy
Classifier: Topic :: Scientific/Engineering :: Mathematics
Requires-Python: >=3.8.0
License-File: LICENSE.txt
Requires-Dist: pandas>=1.3.0
Requires-Dist: numpy>=1.21.0
Requires-Dist: matplotlib>=3.4.0
Requires-Dist: seaborn>=0.11.0
Provides-Extra: test
Requires-Dist: matplotlib>=3.5.0; extra == "test"
